{
  "videos": [
      {
          "createdAt": "2018-08-18T18:37:37.222Z",
          "modifiedAt": "2018-08-18T18:37:37.222Z",
          "description": "When a genetic experiment goes awry, it unleashes super creatures that rampage the city. Scientist Davis races to secure an antidote to try to save the ape that was once his friend.",
          "genre": [
              {
                  "id": "5b786ccb3b857874dbea3cc8",
                  "name": "Action"
              },
              {
                  "id": "5b786cdf3b857874dbea3cca",
                  "name": "Sci-Fi"
              },
              {
                  "id": "5b786cf13b857874dbea3ccb",
                  "name": "Fantasy"
              }
          ],
          "director": [
              {
                  "id": "5b786def3b857874dbea3ccc",
                  "fullName": "Brad Peyton"
              }
          ],
          "id": "5b78685d3b857874dbea3cc7",
          "name": "Rampage",
          "slug": "rampage",
          "price": "Ksh 100"
      },
      {
          "createdAt": "2018-08-19T18:41:58.094Z",
          "modifiedAt": "2018-08-19T18:41:58.094Z",
          "description": "When her husband dumps her, Deanna (Melissa McCarthy) goes back to college at the same school as her daughter. Embracing freedom, fun and frat boys, Deanna finds her true self.",
          "genre": [
              {
                  "id": "5b79bff57456efa3c58f728e",
                  "name": "Comedy"
              }
          ],
          "director": [
              {
                  "id": "5b79c0521f9431a3f9b39f13",
                  "fullName": "Ben Falcone"
              }
          ],
          "id": "5b79be95b1a546a1ee0e84af",
          "name": "Life of the Party",
          "slug": "life-of-the-party",
          "price": "60"
      }
  ]
}
